CHANGES.txt
MANIFEST.in
README.txt
ZPL.txt
bootstrap.py
buildout.cfg
setup.py
zope/__init__.py
zope.fixers.egg-info/PKG-INFO
zope.fixers.egg-info/SOURCES.txt
zope.fixers.egg-info/dependency_links.txt
zope.fixers.egg-info/entry_points.txt
zope.fixers.egg-info/namespace_packages.txt
zope.fixers.egg-info/not-zip-safe
zope.fixers.egg-info/requires.txt
zope.fixers.egg-info/top_level.txt
zope/fixers/__init__.py
zope/fixers/base.py
zope/fixers/fix_class_provides.py
zope/fixers/fix_implements.py
zope/fixers/fix_implements_only.py
zope/fixers/main.py
zope/fixers/tests.py