Metadata-Version: 1.1
Name: zope.fixers
Version: 1.1.2
Summary: 2to3 fixers for Zope
Home-page: http://svn.zope.org/zope.fixers/
Author: Lennart Regebro
Author-email: regebro@gmail.com
License: ZPL
Keywords: 2to3 python3 zope
Platform: UNKNOWN
Classifier: Programming Language :: Python
Classifier: Programming Language :: Python :: 3
Classifier: Programming Language :: Python :: 3.1
Classifier: Programming Language :: Python :: 3.2
Classifier: Programming Language :: Python :: 3.3
Classifier: Topic :: Software Development :: Libraries :: Python Modules
